ipython_autoimport.py
ipython_autoimport-0.5.1.dist-info/LICENSE.txt
ipython_autoimport-0.5.1.dist-info/METADATA
ipython_autoimport-0.5.1.dist-info/WHEEL
ipython_autoimport-0.5.1.dist-info/top_level.txt
ipython_autoimport-0.5.1.dist-info/RECORD
