Metadata-Version: 2.2
Name: ipython-autoimport
Version: 0.5.1
Summary: Automagically import missing modules in IPython.
Author: Antony Lee
License: zlib
Project-URL: Repository, https://github.com/anntzer/ipython-autoimport
Classifier: Development Status :: 4 - Beta
Classifier: Framework :: IPython
Classifier: License :: OSI Approved :: zlib/libpng License
Classifier: Programming Language :: Python :: 3
Requires-Python: >=3.7
License-File: LICENSE.txt
Requires-Dist: ipython>=4.1
Requires-Dist: importlib_metadata; python_version < "3.8"
